video_streamer/__init__.py
video_streamer/__main__.py
video_streamer/core/__init__.py
video_streamer/core/camera.py
video_streamer/core/config.py
video_streamer/core/fakeimg.jpg
video_streamer/core/streamer.py
video_streamer/core/test_video.avi
video_streamer/core/websockethandler.py
video_streamer/main.py
video_streamer/server.py
video_streamer/ui/static/jsmpeg.min.js
video_streamer/ui/template/index_mjpeg.html
video_streamer/ui/template/index_mpeg1.html
video_streamer/ui/template/jsmpeg.min.js
mxcube_video_streamer-1.8.3.dist-info/METADATA
mxcube_video_streamer-1.8.3.dist-info/WHEEL
mxcube_video_streamer-1.8.3.dist-info/entry_points.txt
mxcube_video_streamer-1.8.3.dist-info/RECORD
