Metadata-Version: 2.3
Name: mxcube_video_streamer
Version: 1.8.3
Summary: FastAPI Based video streamer
License: MIT
Keywords: mxcube,fast-api-streamer,video_streamer,mxcubeweb
Author: Marcus Oskarsson
Author-email: oscarsso@esrf.fr
Maintainer: Marcus Oskarsson
Maintainer-email: oscarsso@esrf.fr
Requires-Python: >=3.10,<3.12
Classifier: Development Status :: 5 - Production/Stable
Classifier: Intended Audience :: Developers
Classifier: Intended Audience :: End Users/Desktop
Classifier: Intended Audience :: Science/Research
Classifier: License :: OSI Approved :: MIT License
Classifier: Natural Language :: English
Classifier: Programming Language :: Python :: 3
Classifier: Programming Language :: Python :: 3.10
Classifier: Programming Language :: Python :: 3.11
Classifier: Topic :: Scientific/Engineering
Requires-Dist: fastapi (>=0.116.1,<0.117.0)
Requires-Dist: numpy (>=1.26.0,<2.0)
Requires-Dist: opencv-python (>=4.10.0.84,<5.0.0.0)
Requires-Dist: pillow (>=10.4.0,<11.0.0)
Requires-Dist: pydantic (>=2.8.2,<2.9.0)
Requires-Dist: pydantic-core (==2.20.1)
Requires-Dist: pydantic-settings (>=2.4.0)
Requires-Dist: redis (>=4.3.5,<5.0.0)
Requires-Dist: requests (>=2.32.4,<3.0.0)
Requires-Dist: typing-extensions (>=4.14.1,<5.0.0)
Requires-Dist: uvicorn (>=0.34.0,<0.35.0)
Project-URL: Documentation, https://mxcube.github.io/video-streamer/
Project-URL: Homepage, http://github.com/mxcube/video-streamer
Project-URL: Repository, http://github.com/mxcube/video-streamer
